calculator/__init__.py
calculator/calculator.py
mcp_calculator_nie-0.6.18.dist-info/METADATA
mcp_calculator_nie-0.6.18.dist-info/WHEEL
mcp_calculator_nie-0.6.18.dist-info/entry_points.txt
mcp_calculator_nie-0.6.18.dist-info/top_level.txt
mcp_calculator_nie-0.6.18.dist-info/RECORD
