Metadata-Version: 2.4
Name: mcp-calculator-nie
Version: 0.6.18
Summary: 标准计算器MCP服务
Requires-Python: >=3.10
Requires-Dist: mcp[cli]>=1.0.0
